jsonSpark/__init__.py
jsonSpark-0.0.2.dist-info/LICENSE
jsonSpark-0.0.2.dist-info/METADATA
jsonSpark-0.0.2.dist-info/WHEEL
jsonSpark-0.0.2.dist-info/top_level.txt
jsonSpark-0.0.2.dist-info/RECORD
