Metadata-Version: 2.1
Name: jsonSpark
Version: 0.0.2
Summary: This is a wrapper package for pyspark to process json files. It pythonifies the json pyspark object.
Home-page: https://github.com/mzmmoazam/jsonSpark
Author: mzm
Author-email: mzm.moazam@gmail.com
License: UNKNOWN
Platform: UNKNOWN
Classifier: Programming Language :: Python :: 3
Classifier: License :: OSI Approved :: MIT License
Classifier: Operating System :: OS Independent
Requires-Python: >=3.6
Requires-Dist: py4j (==0.10.9)
Requires-Dist: pyspark (==3.1.1)
Requires-Dist: jsonspark (==0.0.1)
